rutifu/__init__.py
rutifu/rutifu.py
rutifu-0.0.8.dist-info/LICENSE
rutifu-0.0.8.dist-info/METADATA
rutifu-0.0.8.dist-info/WHEEL
rutifu-0.0.8.dist-info/top_level.txt
rutifu-0.0.8.dist-info/RECORD
