Metadata-Version: 2.1
Name: rutifu
Version: 0.0.8
Summary: RUTIFU - Random Utilities That I Find Useful
Author-email: Joe Buehl <jbuehl@buehltech.com>
Project-URL: Homepage, https://github.com/jbuehl/rutifu
Project-URL: Bug Tracker, https://github.com/jbuehl/rutifu/issues
Classifier: Programming Language :: Python :: 3
Classifier: License :: OSI Approved :: GNU General Public License (GPL)
Classifier: Operating System :: POSIX :: Linux
Classifier: Topic :: Software Development :: Libraries :: Python Modules
Requires-Python: >=3.5
License-File: LICENSE
